popgen_dashboards/__init__.py
popgen_dashboards/arg.py
popgen_dashboards/arg_dashboard.py
popgen_dashboards/index.py
popgen_dashboards/assets/dashboard.css
popgen_dashboards/assets/tabs.css
popgen_dashboards-1.1.5.dist-info/LICENSE
popgen_dashboards-1.1.5.dist-info/METADATA
popgen_dashboards-1.1.5.dist-info/WHEEL
popgen_dashboards-1.1.5.dist-info/entry_points.txt
popgen_dashboards-1.1.5.dist-info/top_level.txt
popgen_dashboards-1.1.5.dist-info/RECORD
