Metadata-Version: 2.1
Name: popgen-dashboards
Version: 1.1.5
Summary: Short description
Home-page: https://github.com/kaspermunch/popgen_dashboards
Author: Kasper Munch
Author-email: kaspermunch@birc.au.dk
Requires-Python: >=3.6
License-File: LICENSE
Requires-Dist: jupyterlab
Requires-Dist: dash
Requires-Dist: dash-bootstrap-components
Requires-Dist: pandas
Requires-Dist: networkx
